{"chnlGrp":[],"hd":{"fFileSignature":"Neuralynx","nOperationMode":3,"lActualEpisodes":1,"nADCNumChannels":20,"adBitVolts":[1.52587890625E-7,1.52587890625E-7,1.52587890625E-7,1.52587890625E-7,1.52587890625E-7,1.52587890625E-7,1.52587890625E-7,1.52587890625E-7,1.52587890625E-7,1.52587890625E-7,1.52587890625E-7,1.52587890625E-7,1.52587890625E-7,1.52587890625E-7,1.52587890625E-7,1.52587890625E-7,1.52587890625E-6,3.0517578125E-8,3.0517578125E-8,3.0517578125E-8],"dspDelay_mks":[0,0,0,0,0,0,0,0,0,0,0,0,0,0,0,0,0,0,0,0],"adBitVoltsSpk":[0,0,0,0,0,0,0,0,0,0,0,0,0,0,0,0,0,0,0,0],"dspDelay_mksSpk":[0,0,0,0,0,0,0,0,0,0,0,0,0,0,0,0,0,0,0,0],"alignmentPt":[0,0,0,0,0,0,0,0,0,0,0,0,0,0,0,0,0,0,0,0],"inverted":[0,0,0,0,0,0,0,0,0,0,0,0,0,0,0,0,0,1,1,0],"recChUnits":["µV","µV","µV","µV","µV","µV","µV","µV","µV","µV","µV","µV","µV","µV","µV","µV","µV","µV","µV","µV"],"recChNames":["CSC1","CSC2","CSC3","CSC4","CSC5","CSC6","CSC7","CSC8","CSC9","CSC10","CSC11","CSC12","CSC13","CSC14","CSC15","CSC16","BRL17","BRL18","PZO19","PZO20"],"recChDurations":[5.04656E+8,5.04656E+8,5.04656E+8,5.04656E+8,5.04656E+8,5.04656E+8,5.04656E+8,5.04656E+8,5.04656E+8,5.04656E+8,5.04656E+8,5.04656E+8,5.04656E+8,5.04656E+8,5.04656E+8,5.04656E+8,5.04656E+8,0,0,0],"ch_si":[31.25,31.25,31.25,31.25,31.25,31.25,31.25,31.25,31.25,31.25,31.25,31.25,31.25,31.25,31.25,31.25,31.25,null,null,null],"dataPtsPerChan":[1.6148992E+7,1.6148992E+7,1.6148992E+7,1.6148992E+7,1.6148992E+7,1.6148992E+7,1.6148992E+7,1.6148992E+7,1.6148992E+7,1.6148992E+7,1.6148992E+7,1.6148992E+7,1.6148992E+7,1.6148992E+7,1.6148992E+7,1.6148992E+7,1.6148992E+7,0,0,0],"DSPLowCutFilterEnabled":[true,true,true,true,true,true,true,true,true,true,true,true,true,true,true,true,true,true,true,false],"DspLowCutFrequency":[0.1,0.1,0.1,0.1,0.1,0.1,0.1,0.1,0.1,0.1,0.1,0.1,0.1,0.1,0.1,0.1,0.1,0.1,0.1,0.1],"DSPHighCutFilterEnabled":[true,true,true,true,true,true,true,true,true,true,true,true,true,true,true,true,true,true,true,true],"DspHighCutFrequency":[8000,8000,8000,8000,8000,8000,8000,8000,8000,8000,8000,8000,8000,8000,8000,8000,8000,8000,8000,8000],"dataPts":2.74532864E+8,"si":31.25,"fADCSampleInterval":31.25,"TTLs":[0,16,0,16,0,16,0,16,0,16,0,16,0,16,0,16,0,16,0,16,0,16,0,16,0,16,0,16,0,16,0,16,0,16,0,16,0,16,0,16,0,16,0,16,0,16,0,16,0,16,0,16,0,16,0,16,0,16,0,16,0,16,0,16,0,16,0,16,0,16,0,16,0,16,0,16,0,16,0,16,0,16,0,16,0,16,0,16,0,16,0,16,0,16,0,16,0,16,0,16,0,16,0,0],"EventStrings":["Starting Recording","TTL Input on AcqSystem1_0 board 0 port 0 value (0x0010).","TTL Input on AcqSystem1_0 board 0 port 0 value (0x0000).","TTL Input on AcqSystem1_0 board 0 port 0 value (0x0010).","TTL Input on AcqSystem1_0 board 0 port 0 value (0x0000).","TTL Input on AcqSystem1_0 board 0 port 0 value (0x0010).","TTL Input on AcqSystem1_0 board 0 port 0 value (0x0000).","TTL Input on AcqSystem1_0 board 0 port 0 value (0x0010).","TTL Input on AcqSystem1_0 board 0 port 0 value (0x0000).","TTL Input on AcqSystem1_0 board 0 port 0 value (0x0010).","TTL Input on AcqSystem1_0 board 0 port 0 value (0x0000).","TTL Input on AcqSystem1_0 board 0 port 0 value (0x0010).","TTL Input on AcqSystem1_0 board 0 port 0 value (0x0000).","TTL Input on AcqSystem1_0 board 0 port 0 value (0x0010).","TTL Input on AcqSystem1_0 board 0 port 0 value (0x0000).","TTL Input on AcqSystem1_0 board 0 port 0 value (0x0010).","TTL Input on AcqSystem1_0 board 0 port 0 value (0x0000).","TTL Input on AcqSystem1_0 board 0 port 0 value (0x0010).","TTL Input on AcqSystem1_0 board 0 port 0 value (0x0000).","TTL Input on AcqSystem1_0 board 0 port 0 value (0x0010).","TTL Input on AcqSystem1_0 board 0 port 0 value (0x0000).","TTL Input on AcqSystem1_0 board 0 port 0 value (0x0010).","TTL Input on AcqSystem1_0 board 0 port 0 value (0x0000).","TTL Input on AcqSystem1_0 board 0 port 0 value (0x0010).","TTL Input on AcqSystem1_0 board 0 port 0 value (0x0000).","TTL Input on AcqSystem1_0 board 0 port 0 value (0x0010).","TTL Input on AcqSystem1_0 board 0 port 0 value (0x0000).","TTL Input on AcqSystem1_0 board 0 port 0 value (0x0010).","TTL Input on AcqSystem1_0 board 0 port 0 value (0x0000).","TTL Input on AcqSystem1_0 board 0 port 0 value (0x0010).","TTL Input on AcqSystem1_0 board 0 port 0 value (0x0000).","TTL Input on AcqSystem1_0 board 0 port 0 value (0x0010).","TTL Input on AcqSystem1_0 board 0 port 0 value (0x0000).","TTL Input on AcqSystem1_0 board 0 port 0 value (0x0010).","TTL Input on AcqSystem1_0 board 0 port 0 value (0x0000).","TTL Input on AcqSystem1_0 board 0 port 0 value (0x0010).","TTL Input on AcqSystem1_0 board 0 port 0 value (0x0000).","TTL Input on AcqSystem1_0 board 0 port 0 value (0x0010).","TTL Input on AcqSystem1_0 board 0 port 0 value (0x0000).","TTL Input on AcqSystem1_0 board 0 port 0 value (0x0010).","TTL Input on AcqSystem1_0 board 0 port 0 value (0x0000).","TTL Input on AcqSystem1_0 board 0 port 0 value (0x0010).","TTL Input on AcqSystem1_0 board 0 port 0 value (0x0000).","TTL Input on AcqSystem1_0 board 0 port 0 value (0x0010).","TTL Input on AcqSystem1_0 board 0 port 0 value (0x0000).","TTL Input on AcqSystem1_0 board 0 port 0 value (0x0010).","TTL Input on AcqSystem1_0 board 0 port 0 value (0x0000).","TTL Input on AcqSystem1_0 board 0 port 0 value (0x0010).","TTL Input on AcqSystem1_0 board 0 port 0 value (0x0000).","TTL Input on AcqSystem1_0 board 0 port 0 value (0x0010).","TTL Input on AcqSystem1_0 board 0 port 0 value (0x0000).","TTL Input on AcqSystem1_0 board 0 port 0 value (0x0010).","TTL Input on AcqSystem1_0 board 0 port 0 value (0x0000).","TTL Input on AcqSystem1_0 board 0 port 0 value (0x0010).","TTL Input on AcqSystem1_0 board 0 port 0 value (0x0000).","TTL Input on AcqSystem1_0 board 0 port 0 value (0x0010).","TTL Input on AcqSystem1_0 board 0 port 0 value (0x0000).","TTL Input on AcqSystem1_0 board 0 port 0 value (0x0010).","TTL Input on AcqSystem1_0 board 0 port 0 value (0x0000).","TTL Input on AcqSystem1_0 board 0 port 0 value (0x0010).","TTL Input on AcqSystem1_0 board 0 port 0 value (0x0000).","TTL Input on AcqSystem1_0 board 0 port 0 value (0x0010).","TTL Input on AcqSystem1_0 board 0 port 0 value (0x0000).","TTL Input on AcqSystem1_0 board 0 port 0 value (0x0010).","TTL Input on AcqSystem1_0 board 0 port 0 value (0x0000).","TTL Input on AcqSystem1_0 board 0 port 0 value (0x0010).","TTL Input on AcqSystem1_0 board 0 port 0 value (0x0000).","TTL Input on AcqSystem1_0 board 0 port 0 value (0x0010).","TTL Input on AcqSystem1_0 board 0 port 0 value (0x0000).","TTL Input on AcqSystem1_0 board 0 port 0 value (0x0010).","TTL Input on AcqSystem1_0 board 0 port 0 value (0x0000).","TTL Input on AcqSystem1_0 board 0 port 0 value (0x0010).","TTL Input on AcqSystem1_0 board 0 port 0 value (0x0000).","TTL Input on AcqSystem1_0 board 0 port 0 value (0x0010).","TTL Input on AcqSystem1_0 board 0 port 0 value (0x0000).","TTL Input on AcqSystem1_0 board 0 port 0 value (0x0010).","TTL Input on AcqSystem1_0 board 0 port 0 value (0x0000).","TTL Input on AcqSystem1_0 board 0 port 0 value (0x0010).","TTL Input on AcqSystem1_0 board 0 port 0 value (0x0000).","TTL Input on AcqSystem1_0 board 0 port 0 value (0x0010).","TTL Input on AcqSystem1_0 board 0 port 0 value (0x0000).","TTL Input on AcqSystem1_0 board 0 port 0 value (0x0010).","TTL Input on AcqSystem1_0 board 0 port 0 value (0x0000).","TTL Input on AcqSystem1_0 board 0 port 0 value (0x0010).","TTL Input on AcqSystem1_0 board 0 port 0 value (0x0000).","TTL Input on AcqSystem1_0 board 0 port 0 value (0x0010).","TTL Input on AcqSystem1_0 board 0 port 0 value (0x0000).","TTL Input on AcqSystem1_0 board 0 port 0 value (0x0010).","TTL Input on AcqSystem1_0 board 0 port 0 value (0x0000).","TTL Input on AcqSystem1_0 board 0 port 0 value (0x0010).","TTL Input on AcqSystem1_0 board 0 port 0 value (0x0000).","TTL Input on AcqSystem1_0 board 0 port 0 value (0x0010).","TTL Input on AcqSystem1_0 board 0 port 0 value (0x0000).","TTL Input on AcqSystem1_0 board 0 port 0 value (0x0010).","TTL Input on AcqSystem1_0 board 0 port 0 value (0x0000).","TTL Input on AcqSystem1_0 board 0 port 0 value (0x0010).","TTL Input on AcqSystem1_0 board 0 port 0 value (0x0000).","TTL Input on AcqSystem1_0 board 0 port 0 value (0x0010).","TTL Input on AcqSystem1_0 board 0 port 0 value (0x0000).","TTL Input on AcqSystem1_0 board 0 port 0 value (0x0010).","TTL Input on AcqSystem1_0 board 0 port 0 value (0x0000).","TTL Input on AcqSystem1_0 board 0 port 0 value (0x0010).","TTL Input on AcqSystem1_0 board 0 port 0 value (0x0000).","Stopping Recording"],"recTime":[61981.000001728535,62485.0000038743],"inTTL_timestamps":{"t":[[2.733452E+6,2.733514E+6],[1.2731979E+7,1.2732041E+7],[2.2730381E+7,2.2730444E+7],[3.2728908E+7,3.2728971E+7],[4.272731E+7,4.2727373E+7],[5.2725838E+7,5.27259E+7],[6.272424E+7,6.2724302E+7],[7.2722767E+7,7.272283E+7],[8.2721169E+7,8.2721232E+7],[9.2719697E+7,9.2719759E+7],[1.02718099E+8,1.02718161E+8],[1.12716501E+8,1.12716564E+8],[1.22715028E+8,1.22715091E+8],[1.32713431E+8,1.32713493E+8],[1.42711958E+8,1.4271202E+8],[1.5271036E+8,1.52710423E+8],[1.62708887E+8,1.6270895E+8],[1.7270729E+8,1.72707352E+8],[1.82705817E+8,1.82705879E+8],[1.92704219E+8,1.92704282E+8],[2.02702746E+8,2.02702809E+8],[2.12701148E+8,2.12701211E+8],[2.22699676E+8,2.22699738E+8],[2.32698078E+8,2.3269814E+8],[2.42696605E+8,2.42696668E+8],[2.52695007E+8,2.5269507E+8],[2.6269341E+8,2.62693472E+8],[2.72691937E+8,2.72691999E+8],[2.82690339E+8,2.82690402E+8],[2.92688866E+8,2.92688929E+8],[3.02687269E+8,3.02687331E+8],[3.12685796E+8,3.12685858E+8],[3.22684198E+8,3.22684261E+8],[3.32682725E+8,3.32682788E+8],[3.42681128E+8,3.4268119E+8],[3.52679655E+8,3.52679717E+8],[3.62678057E+8,3.6267812E+8],[3.72676584E+8,3.72676647E+8],[3.82674986E+8,3.82675049E+8],[3.92673514E+8,3.92673576E+8],[4.02671916E+8,4.02671978E+8],[4.12670443E+8,4.12670506E+8],[4.22668845E+8,4.22668908E+8],[4.32667373E+8,4.32667435E+8],[4.42665775E+8,4.42665837E+8],[4.52664302E+8,4.52664365E+8],[4.62662704E+8,4.62662767E+8],[4.72661107E+8,4.72661169E+8],[4.82659634E+8,4.82659696E+8],[4.92658036E+8,4.92658099E+8],[5.02656563E+8,5.02656626E+8]]},"sweepStartInPts":[0,1.6148985504E+7]},"lfp":[504656,20],"lfpVar":[3.8361781296596931,3.9269680116173111,5.111958220447403,4.0275811979838565,3.8401677850740477,4.2261266983395736,4.1795033156664942,12.5612982095057,4.7371798901493172,4.6546480595526614,7.65259046129378,13.78259482002322,4.156081937483262,13.582804535677868,6.1550481727832818,6.1974656225912259,68.525943500362416,null,null,null],"spks":[20,1],"zavp":{"file":"D:\\CheetahData\\2023-11-30\\2023-11-30_17-12-49\\","siS":3.125E-5,"dwnSmplFrq":1000,"stimCh":null,"realStim":{"r":[87470.464,407423.328,727372.192,1.047325056E+6,1.36727392E+6,1.687226816E+6,2.00717568E+6,2.327128544E+6,2.647077408E+6,2.967030304E+6,3.286979168E+6,3.606928032E+6,3.926880896E+6,4.246829792E+6,4.566782656E+6,4.88673152E+6,5.206684384E+6,5.52663328E+6,5.846586144E+6,6.166535008E+6,6.486487872E+6,6.806436736E+6,7.126389632E+6,7.446338496E+6,7.76629136E+6,8.086240224E+6,8.40618912E+6,8.726141984E+6,9.046090848E+6,9.366043712E+6,9.685992608E+6,1.0005945472E+7,1.0325894336E+7,1.06458472E+7,1.0965796096E+7,1.128574896E+7,1.1605697824E+7,1.1925650688E+7,1.2245599552E+7,1.2565552448E+7,1.2885501312E+7,1.3205454176E+7,1.352540304E+7,1.3845355936E+7,1.41653048E+7,1.4485257664E+7,1.4805206528E+7,1.5125155424E+7,1.5445108288E+7,1.5765057152E+7,1.6085010016E+7],"f":[87472.448,407425.312,727374.208,1.047327072E+6,1.367275936E+6,1.6872288E+6,2.007177664E+6,2.32713056E+6,2.647079424E+6,2.967032288E+6,3.286981152E+6,3.606930048E+6,3.926882912E+6,4.246831776E+6,4.56678464E+6,4.886733536E+6,5.2066864E+6,5.526635264E+6,5.846588128E+6,6.166537024E+6,6.486489888E+6,6.806438752E+6,7.126391616E+6,7.44634048E+6,7.766293376E+6,8.08624224E+6,8.406191104E+6,8.726143968E+6,9.046092864E+6,9.366045728E+6,9.685994592E+6,1.0005947456E+7,1.0325896352E+7,1.0645849216E+7,1.096579808E+7,1.1285750944E+7,1.160569984E+7,1.1925652704E+7,1.2245601568E+7,1.2565554432E+7,1.2885503296E+7,1.3205456192E+7,1.3525405056E+7,1.384535792E+7,1.4165306784E+7,1.448525968E+7,1.4805208544E+7,1.5125157408E+7,1.5445110272E+7,1.5765059168E+7,1.6085012032E+7]},"rarStep":[32,32,32,32,32,32,32,32,32,32,32,32,32,32,32,32,32,null,null,null]}}